cohortextractor/VERSION
cohortextractor/__init__.py
cohortextractor/codelistlib.py
cohortextractor/cohortextractor.py
cohortextractor/csv_utils.py
cohortextractor/date_expressions.py
cohortextractor/emis_backend.py
cohortextractor/exceptions.py
cohortextractor/expectation_generators.py
cohortextractor/expressions.py
cohortextractor/log_utils.py
cohortextractor/measure.py
cohortextractor/mssql_utils.py
cohortextractor/pandas_utils.py
cohortextractor/patients.py
cohortextractor/process_covariate_definitions.py
cohortextractor/study_definition.py
cohortextractor/therapeutics_utils.py
cohortextractor/tpp_backend.py
cohortextractor/trino_utils.py
cohortextractor/uk_population_bands_2018.csv
cohortextractor/update_custom_medication_dictionary.py
cohortextractor/update_vmp_mapping.py
cohortextractor/validate_dummy_data.py
cohortextractor/dashboards/__init__.py
cohortextractor/dashboards/vaccinations.py
cohortextractor/dashboards/vaccinations_combine.py
cohortextractor/dashboards/vaccinations_extract.py
tests/__init__.py
tests/conftest.py
tests/emis_backend_setup.py
tests/helpers.py
tests/test_codelistlib.py
tests/test_cohortextractor.py
tests/test_date_expressions.py
tests/test_emis_backend.py
tests/test_expectation_generators.py
tests/test_expressions.py
tests/test_logging.py
tests/test_measures.py
tests/test_pandas_utils.py
tests/test_smoketest.py
tests/test_study_definition.py
tests/test_therapeutics_utils.py
tests/test_tpp_backend.py
tests/test_trino_docker_version.py
tests/test_trino_utils.py
tests/test_update_custom_medication_dictionary.py
tests/test_update_vmp_mapping.py
tests/test_validate_dummy_data.py
tests/tpp_backend_setup.py
tests/dashboards/__init__.py
tests/dashboards/test_vaccinations.py
tests/dashboards/test_vaccinations_combine.py
tests/dashboards/test_vaccinations_extract.py
opensafely_cohort_extractor-1.93.3.dist-info/LICENSE
opensafely_cohort_extractor-1.93.3.dist-info/METADATA
opensafely_cohort_extractor-1.93.3.dist-info/WHEEL
opensafely_cohort_extractor-1.93.3.dist-info/entry_points.txt
opensafely_cohort_extractor-1.93.3.dist-info/top_level.txt
opensafely_cohort_extractor-1.93.3.dist-info/RECORD
