Metadata-Version: 2.1
Name: opensafely-cohort-extractor
Version: 1.93.3
Summary: UNKNOWN
Home-page: https://github.com/opensafely/cohort-extractor
Author: OpenSAFELY
Author-email: tech@opensafely.org
License: UNKNOWN
Platform: UNKNOWN
Classifier: License :: OSI Approved :: GNU General Public License v3 (GPLv3)
Requires-Python: >=3.7
Requires-Dist: lz4
Requires-Dist: pyarrow
Requires-Dist: pandas
Requires-Dist: pyyaml
Requires-Dist: requests
Requires-Dist: retry
Requires-Dist: seaborn
Requires-Dist: sqlparse
Requires-Dist: structlog
Requires-Dist: tabulate
Provides-Extra: drivers
Requires-Dist: presto-python-client; extra == "drivers"
Requires-Dist: pymssql; extra == "drivers"
